prismcat/__init__.py
prismcat/prismcat.py
prismcat-2.0.0.dist-info/entry_points.txt
prismcat-2.0.0.dist-info/WHEEL
prismcat-2.0.0.dist-info/METADATA
prismcat-2.0.0.dist-info/RECORD
