Metadata-Version: 2.1
Name: prismcat
Version: 2.0.0
Summary: parse logs and make pretty colors
License: MIT
Author: Tyler F. Carr
Author-email: tcarwash@gmail.com
Requires-Python: >=3.8,<4.0
Classifier: License :: OSI Approved :: MIT License
Classifier: Programming Language :: Python :: 3
Classifier: Programming Language :: Python :: 3.8
Classifier: Programming Language :: Python :: 3.9
Classifier: Programming Language :: Python :: 3.10
Classifier: Programming Language :: Python :: 3.11
Requires-Dist: ansi2html (>=1.8.0,<2.0.0)
